adversarial_gym/__init__.py
adversarial_gym/adversarial.py
adversarial_gym/chess_env.py
adversarial_gym/tictactoe_env.py
adversarial_gym-0.0.4.dist-info/METADATA
adversarial_gym-0.0.4.dist-info/WHEEL
adversarial_gym-0.0.4.dist-info/top_level.txt
adversarial_gym-0.0.4.dist-info/RECORD
