Metadata-Version: 2.2
Name: adversarial_gym
Version: 0.0.4
Summary: OpenAI Gym environments for adversarial games for the operation beat ourselves organisation.
Home-page: https://github.com/OperationBeatMeChess/adversarial-gym
Author: Dawson Horvath
Author-email: Keith Gordon <keith.gordon9@gmail.com>, Dawson Horvath <horvath.dawson@gmail.com>
License: MIT License
Project-URL: Homepage, https://github.com/OperationBeatMeChess/adversarial-gym
Project-URL: Bug Tracker, https://github.com/OperationBeatMeChess/adversarial-gym/issues
Classifier: Programming Language :: Python :: 3
Classifier: License :: OSI Approved :: MIT License
Classifier: Operating System :: OS Independent
Requires-Python: >=3.7
Dynamic: author
Dynamic: home-page
